blackfortpay/__init__.py
blackfortpay-0.0.1.dist-info/LICENSE
blackfortpay-0.0.1.dist-info/METADATA
blackfortpay-0.0.1.dist-info/WHEEL
blackfortpay-0.0.1.dist-info/top_level.txt
blackfortpay-0.0.1.dist-info/RECORD
