Metadata-Version: 2.1
Name: blackfortpay
Version: 0.0.1
Summary: BlackFort Payment API client
Home-page: https://github.com/panwaclaw/blackfortpay
Author: panwaclaw
Author-email: vkozlovsk@gmail.com
License: UNKNOWN
Platform: UNKNOWN
Classifier: Programming Language :: Python :: 3.6
Classifier: License :: OSI Approved :: MIT License
Classifier: Operating System :: OS Independent
Requires-Python: >=3.6
Requires-Dist: requests (>=2.13.0)
